{
	"backtrace" : 1,
	"backtraceGraph" : 
	{
		"commands" : 
		[
			"add_custom_target"
		],
		"files" : 
		[
			"src/FirmwarePlugin/APM/CMakeLists.txt"
		],
		"nodes" : 
		[
			{
				"file" : 0
			},
			{
				"command" : 0,
				"file" : 0,
				"line" : 1,
				"parent" : 0
			}
		]
	},
	"id" : "APMFirmwarePluginQml::@9e65894a22dd98062e64",
	"name" : "APMFirmwarePluginQml",
	"paths" : 
	{
		"build" : "src/FirmwarePlugin/APM",
		"source" : "src/FirmwarePlugin/APM"
	},
	"sourceGroups" : 
	[
		{
			"name" : "",
			"sourceIndexes" : 
			[
				0
			]
		}
	],
	"sources" : 
	[
		{
			"backtrace" : 1,
			"path" : "src/FirmwarePlugin/APM/APMSensorParams.qml",
			"sourceGroupIndex" : 0
		}
	],
	"type" : "UTILITY"
}
