{
	"backtrace" : 1,
	"backtraceGraph" : 
	{
		"commands" : 
		[
			"add_custom_target"
		],
		"files" : 
		[
			"src/VehicleSetup/CMakeLists.txt"
		],
		"nodes" : 
		[
			{
				"file" : 0
			},
			{
				"command" : 0,
				"file" : 0,
				"line" : 17,
				"parent" : 0
			}
		]
	},
	"id" : "VehicleSetupQml::@6870a015836745ded890",
	"name" : "VehicleSetupQml",
	"paths" : 
	{
		"build" : "src/VehicleSetup",
		"source" : "src/VehicleSetup"
	},
	"sourceGroups" : 
	[
		{
			"name" : "",
			"sourceIndexes" : 
			[
				0,
				1,
				2,
				3,
				4,
				5,
				6,
				7,
				8,
				9
			]
		}
	],
	"sources" : 
	[
		{
			"backtrace" : 1,
			"path" : "src/VehicleSetup/FirmwareUpgrade.qml",
			"sourceGroupIndex" : 0
		},
		{
			"backtrace" : 1,
			"path" : "src/VehicleSetup/JoystickConfigAdvanced.qml",
			"sourceGroupIndex" : 0
		},
		{
			"backtrace" : 1,
			"path" : "src/VehicleSetup/JoystickConfigButtons.qml",
			"sourceGroupIndex" : 0
		},
		{
			"backtrace" : 1,
			"path" : "src/VehicleSetup/JoystickConfigCalibration.qml",
			"sourceGroupIndex" : 0
		},
		{
			"backtrace" : 1,
			"path" : "src/VehicleSetup/JoystickConfigGeneral.qml",
			"sourceGroupIndex" : 0
		},
		{
			"backtrace" : 1,
			"path" : "src/VehicleSetup/JoystickConfig.qml",
			"sourceGroupIndex" : 0
		},
		{
			"backtrace" : 1,
			"path" : "src/VehicleSetup/PX4FlowSensor.qml",
			"sourceGroupIndex" : 0
		},
		{
			"backtrace" : 1,
			"path" : "src/VehicleSetup/SetupParameterEditor.qml",
			"sourceGroupIndex" : 0
		},
		{
			"backtrace" : 1,
			"path" : "src/VehicleSetup/SetupView.qml",
			"sourceGroupIndex" : 0
		},
		{
			"backtrace" : 1,
			"path" : "src/VehicleSetup/VehicleSummary.qml",
			"sourceGroupIndex" : 0
		}
	],
	"type" : "UTILITY"
}
