{
	"backtrace" : 0,
	"backtraceGraph" : 
	{
		"commands" : [],
		"files" : 
		[
			"src/ADSB/CMakeLists.txt"
		],
		"nodes" : 
		[
			{
				"file" : 0
			}
		]
	},
	"dependencies" : 
	[
		{
			"id" : "ADSB_autogen_timestamp_deps::@4bf27f97029ab5cf12e8"
		}
	],
	"id" : "ADSB_autogen::@4bf27f97029ab5cf12e8",
	"isGeneratorProvided" : true,
	"name" : "ADSB_autogen",
	"paths" : 
	{
		"build" : "src/ADSB",
		"source" : "src/ADSB"
	},
	"sourceGroups" : 
	[
		{
			"name" : "",
			"sourceIndexes" : 
			[
				0
			]
		},
		{
			"name" : "CMake Rules",
			"sourceIndexes" : 
			[
				1,
				2
			]
		}
	],
	"sources" : 
	[
		{
			"backtrace" : 0,
			"isGenerated" : true,
			"path" : "C:/QGC-ROS2/cmakeBuild/src/ADSB/CMakeFiles/ADSB_autogen",
			"sourceGroupIndex" : 0
		},
		{
			"backtrace" : 0,
			"isGenerated" : true,
			"path" : "C:/QGC-ROS2/cmakeBuild/src/ADSB/CMakeFiles/ADSB_autogen.rule",
			"sourceGroupIndex" : 1
		},
		{
			"backtrace" : 0,
			"isGenerated" : true,
			"path" : "C:/QGC-ROS2/cmakeBuild/src/ADSB/ADSB_autogen/timestamp.rule",
			"sourceGroupIndex" : 1
		}
	],
	"type" : "UTILITY"
}
